{
  "meta": {
    "id": "DB2878BD7BC84B0C9250E45A9E7B9682",
    "owner": "vz",
    "format": "JSON",
    "version": "0.2.24",
    "correlation": [],
    "created": "2019-04-24T22:00:02.93+02:00",
    "sequence": 88
  },
  "data": {
    "istformation": {
      "fahrtrichtung": "VORWAERTS",
      "allFahrzeuggruppe": [
        {
          "allFahrzeug": [
            {
              "allFahrzeugausstattung": [],
              "kategorie": "LOK",
              "fahrzeugnummer": "918061465723",
              "orientierung": "UNDEFINIERT",
              "positioningruppe": "1",
              "fahrzeugsektor": "",
              "fahrzeugtyp": "E1465",
              "wagenordnungsnummer": "",
              "positionamhalt": {
                "endemeter": "161.185",
                "endeprozent": "95",
                "startmeter": "142.285",
                "startprozent": "84"
              },
              "status": "OFFEN"
            },
            {
              "allFahrzeugausstattung": [
                {
                  "anzahl": "",
                  "ausstattungsart": "KLIMA",
                  "bezeichnung": "",
                  "status": "UNDEFINIERT"
                }
              ],
              "kategorie": "DOPPELSTOCKWAGENERSTEKLASSE",
              "fahrzeugnummer": "508016811715",
              "orientierung": "UNDEFINIERT",
              "positioningruppe": "2",
              "fahrzeugsektor": "",
              "fahrzeugtyp": "DApza",
              "wagenordnungsnummer": "5",
              "positionamhalt": {
                "endemeter": "142.285",
                "endeprozent": "84",
                "startmeter": "115.485",
                "startprozent": "68"
              },
              "status": "OFFEN"
            },
            {
              "allFahrzeugausstattung": [
                {
                  "anzahl": "",
                  "ausstattungsart": "KLIMA",
                  "bezeichnung": "",
                  "status": "UNDEFINIERT"
                },
                {
                  "anzahl": "1",
                  "ausstattungsart": "PLAETZEFAHRRAD",
                  "bezeichnung": "",
                  "status": "UNDEFINIERT"
                }
              ],
              "kategorie": "DOPPELSTOCKWAGENZWEITEKLASSE",
              "fahrzeugnummer": "508026814022",
              "orientierung": "UNDEFINIERT",
              "positioningruppe": "3",
              "fahrzeugsektor": "",
              "fahrzeugtyp": "DBpza",
              "wagenordnungsnummer": "4",
              "positionamhalt": {
                "endemeter": "115.485",
                "endeprozent": "68",
                "startmeter": "88.685",
                "startprozent": "52"
              },
              "status": "OFFEN"
            },
            {
              "allFahrzeugausstattung": [
                {
                  "anzahl": "",
                  "ausstattungsart": "KLIMA",
                  "bezeichnung": "",
                  "status": "UNDEFINIERT"
                },
                {
                  "anzahl": "1",
                  "ausstattungsart": "PLAETZEFAHRRAD",
                  "bezeichnung": "",
                  "status": "UNDEFINIERT"
                }
              ],
              "kategorie": "DOPPELSTOCKWAGENZWEITEKLASSE",
              "fahrzeugnummer": "508026814691",
              "orientierung": "UNDEFINIERT",
              "positioningruppe": "4",
              "fahrzeugsektor": "",
              "fahrzeugtyp": "DBpza",
              "wagenordnungsnummer": "3",
              "positionamhalt": {
                "endemeter": "88.685",
                "endeprozent": "52",
                "startmeter": "61.885",
                "startprozent": "37"
              },
              "status": "OFFEN"
            },
            {
              "allFahrzeugausstattung": [
                {
                  "anzahl": "",
                  "ausstattungsart": "KLIMA",
                  "bezeichnung": "",
                  "status": "UNDEFINIERT"
                },
                {
                  "anzahl": "1",
                  "ausstattungsart": "PLAETZEFAHRRAD",
                  "bezeichnung": "",
                  "status": "UNDEFINIERT"
                }
              ],
              "kategorie": "DOPPELSTOCKWAGENZWEITEKLASSE",
              "fahrzeugnummer": "508026814683",
              "orientierung": "UNDEFINIERT",
              "positioningruppe": "5",
              "fahrzeugsektor": "",
              "fahrzeugtyp": "DBpza",
              "wagenordnungsnummer": "2",
              "positionamhalt": {
                "endemeter": "61.885",
                "endeprozent": "37",
                "startmeter": "35.085",
                "startprozent": "21"
              },
              "status": "OFFEN"
            },
            {
              "allFahrzeugausstattung": [
                {
                  "anzahl": "",
                  "ausstattungsart": "KLIMA",
                  "bezeichnung": "",
                  "status": "UNDEFINIERT"
                },
                {
                  "anzahl": "6",
                  "ausstattungsart": "PLAETZEFAHRRAD",
                  "bezeichnung": "",
                  "status": "UNDEFINIERT"
                },
                {
                  "anzahl": "",
                  "ausstattungsart": "PLAETZEROLLSTUHL",
                  "bezeichnung": "",
                  "status": "UNDEFINIERT"
                },
                {
                  "anzahl": "",
                  "ausstattungsart": "ROLLSTUHLTOILETTE",
                  "bezeichnung": "",
                  "status": "UNDEFINIERT"
                }
              ],
              "kategorie": "DOPPELSTOCKSTEUERWAGENZWEITEKLASSE",
              "fahrzeugnummer": "508086818731",
              "orientierung": "UNDEFINIERT",
              "positioningruppe": "6",
              "fahrzeugsektor": "",
              "fahrzeugtyp": "DBpbzfa",
              "wagenordnungsnummer": "1",
              "positionamhalt": {
                "endemeter": "35.085",
                "endeprozent": "21",
                "startmeter": "7.815",
                "startprozent": "5"
              },
              "status": "OFFEN"
            }
          ],
          "fahrzeuggruppebezeichnung": "ICD2873",
          "zielbetriebsstellename": "Köln Hbf",
          "startbetriebsstellename": "Leipzig Hbf",
          "verkehrlichezugnummer": "2048"
        }
      ],
      "halt": {
        "abfahrtszeit": "2019-04-25T14:42:00",
        "ankunftszeit": "2019-04-25T14:40:00",
        "bahnhofsname": "Bielefeld Hbf",
        "evanummer": "8000036",
        "gleisbezeichnung": "8",
        "haltid": "EBILP",
        "rl100": "EBILP",
        "allSektor": [
          {
            "positionamgleis": {
              "endemeter": "",
              "endeprozent": "",
              "startmeter": "",
              "startprozent": ""
            },
            "sektorbezeichnung": ""
          }
        ]
      },
      "liniebezeichnung": "55",
      "zuggattung": "IC",
      "zugnummer": "2048",
      "serviceid": "8730768015",
      "planstarttag": "2019-04-25",
      "fahrtid": "",
      "istplaninformation": true
    }
  }
}
