{
  "meta": {
    "id": "CCA27E51FF564D5E8730E70A0501F185",
    "owner": "vz",
    "format": "JSON",
    "version": "0.2.24",
    "correlation": [],
    "created": "2019-04-24T22:00:03.425+02:00",
    "sequence": 25
  },
  "data": {
    "istformation": {
      "fahrtrichtung": "VORWAERTS",
      "allFahrzeuggruppe": [
        {
          "allFahrzeug": [
            {
              "allFahrzeugausstattung": [
                {
                  "anzahl": "",
                  "ausstattungsart": "PLAETZEFAHRRAD",
                  "bezeichnung": "",
                  "status": "UNDEFINIERT"
                }
              ],
              "kategorie": "STEUERWAGENZWEITEKLASSE",
              "fahrzeugnummer": "",
              "orientierung": "UNDEFINIERT",
              "positioningruppe": "1",
              "fahrzeugsektor": "A",
              "fahrzeugtyp": "Bimmdzf",
              "wagenordnungsnummer": "5",
              "positionamhalt": {
                "endemeter": "68.65",
                "endeprozent": "23",
                "startmeter": "42.45",
                "startprozent": "14"
              },
              "status": "OFFEN"
            },
            {
              "allFahrzeugausstattung": [
                {
                  "anzahl": "",
                  "ausstattungsart": "KLIMA",
                  "bezeichnung": "",
                  "status": "UNDEFINIERT"
                }
              ],
              "kategorie": "REISEZUGWAGENZWEITEKLASSE",
              "fahrzeugnummer": "",
              "orientierung": "UNDEFINIERT",
              "positioningruppe": "2",
              "fahrzeugsektor": "B",
              "fahrzeugtyp": "Bpmz",
              "wagenordnungsnummer": "6",
              "positionamhalt": {
                "endemeter": "94.85",
                "endeprozent": "31",
                "startmeter": "68.65",
                "startprozent": "23"
              },
              "status": "OFFEN"
            },
            {
              "allFahrzeugausstattung": [
                {
                  "anzahl": "",
                  "ausstattungsart": "KLIMA",
                  "bezeichnung": "",
                  "status": "UNDEFINIERT"
                }
              ],
              "kategorie": "REISEZUGWAGENZWEITEKLASSE",
              "fahrzeugnummer": "",
              "orientierung": "UNDEFINIERT",
              "positioningruppe": "3",
              "fahrzeugsektor": "B",
              "fahrzeugtyp": "Bpmz",
              "wagenordnungsnummer": "7",
              "positionamhalt": {
                "endemeter": "121.05",
                "endeprozent": "40",
                "startmeter": "94.85",
                "startprozent": "31"
              },
              "status": "OFFEN"
            },
            {
              "allFahrzeugausstattung": [
                {
                  "anzahl": "",
                  "ausstattungsart": "KLIMA",
                  "bezeichnung": "",
                  "status": "UNDEFINIERT"
                }
              ],
              "kategorie": "REISEZUGWAGENZWEITEKLASSE",
              "fahrzeugnummer": "",
              "orientierung": "UNDEFINIERT",
              "positioningruppe": "4",
              "fahrzeugsektor": "C",
              "fahrzeugtyp": "Bpmz",
              "wagenordnungsnummer": "8",
              "positionamhalt": {
                "endemeter": "147.25",
                "endeprozent": "49",
                "startmeter": "121.05",
                "startprozent": "40"
              },
              "status": "OFFEN"
            },
            {
              "allFahrzeugausstattung": [
                {
                  "anzahl": "",
                  "ausstattungsart": "KLIMA",
                  "bezeichnung": "",
                  "status": "UNDEFINIERT"
                },
                {
                  "anzahl": "",
                  "ausstattungsart": "PLAETZEROLLSTUHL",
                  "bezeichnung": "",
                  "status": "UNDEFINIERT"
                },
                {
                  "anzahl": "",
                  "ausstattungsart": "ROLLSTUHLTOILETTE",
                  "bezeichnung": "",
                  "status": "UNDEFINIERT"
                }
              ],
              "kategorie": "REISEZUGWAGENZWEITEKLASSE",
              "fahrzeugnummer": "",
              "orientierung": "UNDEFINIERT",
              "positioningruppe": "5",
              "fahrzeugsektor": "C",
              "fahrzeugtyp": "Bpmbz",
              "wagenordnungsnummer": "9",
              "positionamhalt": {
                "endemeter": "173.45",
                "endeprozent": "58",
                "startmeter": "147.25",
                "startprozent": "49"
              },
              "status": "OFFEN"
            },
            {
              "allFahrzeugausstattung": [
                {
                  "anzahl": "",
                  "ausstattungsart": "KLIMA",
                  "bezeichnung": "",
                  "status": "UNDEFINIERT"
                }
              ],
              "kategorie": "REISEZUGWAGENZWEITEKLASSE",
              "fahrzeugnummer": "",
              "orientierung": "UNDEFINIERT",
              "positioningruppe": "6",
              "fahrzeugsektor": "D",
              "fahrzeugtyp": "Bvmsz",
              "wagenordnungsnummer": "10",
              "positionamhalt": {
                "endemeter": "199.65",
                "endeprozent": "66",
                "startmeter": "173.45",
                "startprozent": "58"
              },
              "status": "OFFEN"
            },
            {
              "allFahrzeugausstattung": [
                {
                  "anzahl": "",
                  "ausstattungsart": "KLIMA",
                  "bezeichnung": "",
                  "status": "UNDEFINIERT"
                }
              ],
              "kategorie": "REISEZUGWAGENERSTEKLASSE",
              "fahrzeugnummer": "",
              "orientierung": "UNDEFINIERT",
              "positioningruppe": "7",
              "fahrzeugsektor": "D",
              "fahrzeugtyp": "Avmz",
              "wagenordnungsnummer": "12",
              "positionamhalt": {
                "endemeter": "225.85",
                "endeprozent": "75",
                "startmeter": "199.65",
                "startprozent": "66"
              },
              "status": "OFFEN"
            }
          ],
          "fahrzeuggruppebezeichnung": "Zug_2200_IC_5_12",
          "zielbetriebsstellename": "Norddeich Mole",
          "startbetriebsstellename": "Köln Hbf",
          "verkehrlichezugnummer": "2200"
        },
        {
          "allFahrzeug": [
            {
              "allFahrzeugausstattung": [],
              "kategorie": "LOK",
              "fahrzeugnummer": "Lok_2200",
              "orientierung": "UNDEFINIERT",
              "positioningruppe": "1",
              "fahrzeugsektor": "E",
              "fahrzeugtyp": "E",
              "wagenordnungsnummer": "",
              "positionamhalt": {
                "endemeter": "245.85",
                "endeprozent": "82",
                "startmeter": "225.85",
                "startprozent": "75"
              },
              "status": "OFFEN"
            }
          ],
          "fahrzeuggruppebezeichnung": "Lok_2200",
          "zielbetriebsstellename": "Norddeich Mole",
          "startbetriebsstellename": "Köln Hbf",
          "verkehrlichezugnummer": "2200"
        }
      ],
      "halt": {
        "abfahrtszeit": "2019-04-25T17:28:00",
        "ankunftszeit": "2019-04-25T17:25:00",
        "bahnhofsname": "Emden Hbf",
        "evanummer": "8001768",
        "gleisbezeichnung": "5",
        "haltid": "HE",
        "rl100": "HE",
        "allSektor": [
          {
            "positionamgleis": {
              "endemeter": "63.3",
              "endeprozent": "21",
              "startmeter": "0",
              "startprozent": "0"
            },
            "sektorbezeichnung": "A"
          },
          {
            "positionamgleis": {
              "endemeter": "112.4",
              "endeprozent": "37",
              "startmeter": "63.3",
              "startprozent": "21"
            },
            "sektorbezeichnung": "B"
          },
          {
            "positionamgleis": {
              "endemeter": "165.25",
              "endeprozent": "55",
              "startmeter": "112.4",
              "startprozent": "37"
            },
            "sektorbezeichnung": "C"
          },
          {
            "positionamgleis": {
              "endemeter": "221.6",
              "endeprozent": "73",
              "startmeter": "165.25",
              "startprozent": "55"
            },
            "sektorbezeichnung": "D"
          },
          {
            "positionamgleis": {
              "endemeter": "301.6",
              "endeprozent": "100",
              "startmeter": "221.6",
              "startprozent": "73"
            },
            "sektorbezeichnung": "E"
          }
        ]
      },
      "liniebezeichnung": "35",
      "zuggattung": "IC",
      "zugnummer": "2200",
      "serviceid": "9152440389",
      "planstarttag": "2019-04-25",
      "fahrtid": "",
      "istplaninformation": true
    }
  }
}
