{
  "meta": {
    "id": "9C1A871FC9F449B08372E583707071D3",
    "owner": "vz",
    "format": "JSON",
    "version": "0.2.24",
    "correlation": [],
    "created": "2019-04-24T22:00:08.685+02:00",
    "sequence": 133
  },
  "data": {
    "istformation": {
      "fahrtrichtung": "VORWAERTS",
      "allFahrzeuggruppe": [
        {
          "allFahrzeug": [
            {
              "allFahrzeugausstattung": [
                {
                  "anzahl": "",
                  "ausstattungsart": "KLIMA",
                  "bezeichnung": "",
                  "status": "UNDEFINIERT"
                }
              ],
              "kategorie": "STEUERWAGENZWEITEKLASSE",
              "fahrzeugnummer": "938054035192",
              "orientierung": "UNDEFINIERT",
              "positioningruppe": "1",
              "fahrzeugsektor": "A",
              "fahrzeugtyp": "Bpmzf",
              "wagenordnungsnummer": "21",
              "positionamhalt": {
                "endemeter": "139.735",
                "endeprozent": "35",
                "startmeter": "114.2",
                "startprozent": "28"
              },
              "status": "OFFEN"
            },
            {
              "allFahrzeugausstattung": [
                {
                  "anzahl": "",
                  "ausstattungsart": "KLIMA",
                  "bezeichnung": "",
                  "status": "UNDEFINIERT"
                }
              ],
              "kategorie": "REISEZUGWAGENZWEITEKLASSE",
              "fahrzeugnummer": "938054036190",
              "orientierung": "UNDEFINIERT",
              "positioningruppe": "2",
              "fahrzeugsektor": "B",
              "fahrzeugtyp": "Bpmz",
              "wagenordnungsnummer": "22",
              "positionamhalt": {
                "endemeter": "164.51",
                "endeprozent": "41",
                "startmeter": "139.735",
                "startprozent": "35"
              },
              "status": "OFFEN"
            },
            {
              "allFahrzeugausstattung": [
                {
                  "anzahl": "",
                  "ausstattungsart": "KLIMA",
                  "bezeichnung": "",
                  "status": "UNDEFINIERT"
                }
              ],
              "kategorie": "REISEZUGWAGENZWEITEKLASSE",
              "fahrzeugnummer": "938054037198",
              "orientierung": "UNDEFINIERT",
              "positioningruppe": "3",
              "fahrzeugsektor": "B",
              "fahrzeugtyp": "Bpmz",
              "wagenordnungsnummer": "23",
              "positionamhalt": {
                "endemeter": "189.285",
                "endeprozent": "47",
                "startmeter": "164.51",
                "startprozent": "41"
              },
              "status": "OFFEN"
            },
            {
              "allFahrzeugausstattung": [
                {
                  "anzahl": "",
                  "ausstattungsart": "KLIMA",
                  "bezeichnung": "",
                  "status": "UNDEFINIERT"
                },
                {
                  "anzahl": "",
                  "ausstattungsart": "PLAETZEROLLSTUHL",
                  "bezeichnung": "",
                  "status": "UNDEFINIERT"
                },
                {
                  "anzahl": "",
                  "ausstattungsart": "ROLLSTUHLTOILETTE",
                  "bezeichnung": "",
                  "status": "UNDEFINIERT"
                }
              ],
              "kategorie": "REISEZUGWAGENZWEITEKLASSE",
              "fahrzeugnummer": "938054038196",
              "orientierung": "UNDEFINIERT",
              "positioningruppe": "4",
              "fahrzeugsektor": "C",
              "fahrzeugtyp": "Bpmbz",
              "wagenordnungsnummer": "25",
              "positionamhalt": {
                "endemeter": "214.06",
                "endeprozent": "53",
                "startmeter": "189.285",
                "startprozent": "47"
              },
              "status": "OFFEN"
            },
            {
              "allFahrzeugausstattung": [],
              "kategorie": "HALBSPEISEWAGENZWEITEKLASSE",
              "fahrzeugnummer": "938054033197",
              "orientierung": "UNDEFINIERT",
              "positioningruppe": "5",
              "fahrzeugsektor": "C",
              "fahrzeugtyp": "BRmz",
              "wagenordnungsnummer": "26",
              "positionamhalt": {
                "endemeter": "238.835",
                "endeprozent": "59",
                "startmeter": "214.06",
                "startprozent": "53"
              },
              "status": "OFFEN"
            },
            {
              "allFahrzeugausstattung": [
                {
                  "anzahl": "",
                  "ausstattungsart": "KLIMA",
                  "bezeichnung": "",
                  "status": "UNDEFINIERT"
                }
              ],
              "kategorie": "REISEZUGWAGENZWEITEKLASSE",
              "fahrzeugnummer": "938054032199",
              "orientierung": "UNDEFINIERT",
              "positioningruppe": "6",
              "fahrzeugsektor": "D",
              "fahrzeugtyp": "Bvmz",
              "wagenordnungsnummer": "27",
              "positionamhalt": {
                "endemeter": "263.61",
                "endeprozent": "65",
                "startmeter": "238.835",
                "startprozent": "59"
              },
              "status": "OFFEN"
            },
            {
              "allFahrzeugausstattung": [
                {
                  "anzahl": "",
                  "ausstattungsart": "KLIMA",
                  "bezeichnung": "",
                  "status": "UNDEFINIERT"
                }
              ],
              "kategorie": "REISEZUGWAGENERSTEKLASSE",
              "fahrzeugnummer": "938054031316",
              "orientierung": "UNDEFINIERT",
              "positioningruppe": "7",
              "fahrzeugsektor": "D",
              "fahrzeugtyp": "Avmz",
              "wagenordnungsnummer": "28",
              "positionamhalt": {
                "endemeter": "288.385",
                "endeprozent": "71",
                "startmeter": "263.61",
                "startprozent": "65"
              },
              "status": "OFFEN"
            },
            {
              "allFahrzeugausstattung": [
                {
                  "anzahl": "",
                  "ausstattungsart": "KLIMA",
                  "bezeichnung": "",
                  "status": "UNDEFINIERT"
                }
              ],
              "kategorie": "STEUERWAGENERSTEKLASSE",
              "fahrzeugnummer": "938054030144",
              "orientierung": "UNDEFINIERT",
              "positioningruppe": "8",
              "fahrzeugsektor": "E",
              "fahrzeugtyp": "Apmzf",
              "wagenordnungsnummer": "29",
              "positionamhalt": {
                "endemeter": "314.52",
                "endeprozent": "78",
                "startmeter": "288.385",
                "startprozent": "71"
              },
              "status": "OFFEN"
            }
          ],
          "fahrzeuggruppebezeichnung": "ICE0319",
          "zielbetriebsstellename": "Essen Hbf",
          "startbetriebsstellename": "Nürnberg Hbf",
          "verkehrlichezugnummer": "824"
        }
      ],
      "halt": {
        "abfahrtszeit": "2019-04-25T08:38:00",
        "ankunftszeit": "2019-04-25T08:36:00",
        "bahnhofsname": "Düsseldorf Hbf",
        "evanummer": "8000085",
        "gleisbezeichnung": "18",
        "haltid": "KD",
        "rl100": "KD",
        "allSektor": [
          {
            "positionamgleis": {
              "endemeter": "137.825",
              "endeprozent": "34",
              "startmeter": "0",
              "startprozent": "0"
            },
            "sektorbezeichnung": "A"
          },
          {
            "positionamgleis": {
              "endemeter": "188.325",
              "endeprozent": "46",
              "startmeter": "137.825",
              "startprozent": "34"
            },
            "sektorbezeichnung": "B"
          },
          {
            "positionamgleis": {
              "endemeter": "237.825",
              "endeprozent": "59",
              "startmeter": "188.325",
              "startprozent": "46"
            },
            "sektorbezeichnung": "C"
          },
          {
            "positionamgleis": {
              "endemeter": "291.4",
              "endeprozent": "72",
              "startmeter": "237.825",
              "startprozent": "59"
            },
            "sektorbezeichnung": "D"
          },
          {
            "positionamgleis": {
              "endemeter": "405",
              "endeprozent": "100",
              "startmeter": "291.4",
              "startprozent": "72"
            },
            "sektorbezeichnung": "E"
          }
        ]
      },
      "liniebezeichnung": "41",
      "zuggattung": "ICE",
      "zugnummer": "824",
      "serviceid": "3326234013",
      "planstarttag": "2019-04-25",
      "fahrtid": "",
      "istplaninformation": true
    }
  }
}
